jko_rotating_loggers/__init__.py
jko_rotating_loggers/loggers.py
jko_rotating_loggers-0.0.3.dist-info/LICENSE
jko_rotating_loggers-0.0.3.dist-info/METADATA
jko_rotating_loggers-0.0.3.dist-info/WHEEL
jko_rotating_loggers-0.0.3.dist-info/top_level.txt
jko_rotating_loggers-0.0.3.dist-info/RECORD
