Metadata-Version: 2.1
Name: jko-rotating-loggers
Version: 0.0.3
Summary: A time rotating log
Home-page: https://github.com/pypa/sampleproject
Author: Roy Hung
Author-email: roy.hung@jkos.com
License: UNKNOWN
Platform: UNKNOWN
Classifier: Programming Language :: Python :: 3
Classifier: License :: OSI Approved :: MIT License
Classifier: Operating System :: OS Independent
